split_types/__init__.py
split_types/message_types.py
split_types/transaction.py
split_types/user.py
split_types-0.0.5.dist-info/LICENSE
split_types-0.0.5.dist-info/METADATA
split_types-0.0.5.dist-info/WHEEL
split_types-0.0.5.dist-info/top_level.txt
split_types-0.0.5.dist-info/RECORD
