Metadata-Version: 2.1
Name: split-types
Version: 0.0.5
Summary: Types for Split
Home-page: https://github.com/benleong0/split/split_types
Author: Ben Leong
Author-email: Ben Leong <author@example.com>
License: Copyright (c) 2018 The Python Packaging Authority        
Project-URL: Homepage, https://github.com/benleong0/split
Classifier: Programming Language :: Python :: 3
Classifier: License :: OSI Approved :: MIT License
Classifier: Operating System :: OS Independent
Requires-Python: >=3.8
License-File: LICENSE
